{
	"$schema": "http://schema.management.azure.com/schemas/2015-01-01/deploymentTemplate.json#",
	"contentVersion": "1.0.0.0",
	"parameters": {
		"factoryName": {
			"type": "string",
			"metadata": "Data Factory name",
			"defaultValue": "krishanadatafactory2"
		},
		"AzureBlobStorage1_connectionString": {
			"type": "secureString",
			"metadata": "Secure string for 'connectionString' of 'AzureBlobStorage1'"
		},
		"AzureDataLakeStorage1_accountKey": {
			"type": "secureString",
			"metadata": "Secure string for 'accountKey' of 'AzureDataLakeStorage1'"
		},
		"directaccountAzureBlobStorage1_connectionString": {
			"type": "secureString",
			"metadata": "Secure string for 'connectionString' of 'directaccountAzureBlobStorage1'"
		},
		"AzureBlobStorage1bysasmethod_sasUri": {
			"type": "secureString",
			"metadata": "Secure string for 'sasUri' of 'AzureBlobStorage1bysasmethod'"
		},
		"AzureBlobStorage1magedidentity_properties_typeProperties_serviceEndpoint": {
			"type": "string",
			"defaultValue": "https://krishanastoarge.blob.core.windows.net/"
		},
		"AzureDataLakeStorage1_properties_typeProperties_url": {
			"type": "string",
			"defaultValue": "https://krishanastoarge.dfs.core.windows.net/"
		},
		"AzureKeyVault1_properties_typeProperties_baseUrl": {
			"type": "string",
			"defaultValue": "https://valutaccesskey.vault.azure.net/"
		},
		"AzureSqlDatabase1_properties_typeProperties_server": {
			"type": "string",
			"defaultValue": "ramaserver2.database.windows.net"
		},
		"AzureSqlDatabase1_properties_typeProperties_database": {
			"type": "string",
			"defaultValue": "RAMADB"
		},
		"RestService1_properties_typeProperties_url": {
			"type": "string",
			"defaultValue": "https://cat-fact.herokuapp.com/facts"
		}
	},
	"variables": {
		"factoryId": "[concat('Microsoft.DataFactory/factories/', parameters('factoryName'))]"
	},
	"resources": [
		{
			"name": "[concat(parameters('factoryName'), '/child piepline')]",
			"type": "Microsoft.DataFactory/factories/pipelines",
			"apiVersion": "2018-06-01",
			"properties": {
				"activities": [
					{
						"name": "Wait1",
						"type": "Wait",
						"dependsOn": [],
						"userProperties": [],
						"typeProperties": {
							"waitTimeInSeconds": 15
						}
					}
				],
				"policy": {
					"elapsedTimeMetric": {}
				},
				"annotations": []
			},
			"dependsOn": []
		},
		{
			"name": "[concat(parameters('factoryName'), '/child2_pipeline1')]",
			"type": "Microsoft.DataFactory/factories/pipelines",
			"apiVersion": "2018-06-01",
			"properties": {
				"activities": [
					{
						"name": "Wait1",
						"type": "Wait",
						"dependsOn": [],
						"userProperties": [],
						"typeProperties": {
							"waitTimeInSeconds": 32
						}
					}
				],
				"policy": {
					"elapsedTimeMetric": {}
				},
				"annotations": []
			},
			"dependsOn": []
		},
		{
			"name": "[concat(parameters('factoryName'), '/AzureBlobStorage1')]",
			"type": "Microsoft.DataFactory/factories/linkedServices",
			"apiVersion": "2018-06-01",
			"properties": {
				"parameters": {
					"global": {
						"type": "string"
					}
				},
				"annotations": [],
				"type": "AzureBlobStorage",
				"typeProperties": {
					"connectionString": "[parameters('AzureBlobStorage1_connectionString')]"
				}
			},
			"dependsOn": []
		},
		{
			"name": "[concat(parameters('factoryName'), '/AzureBlobStorage1bysasmethod')]",
			"type": "Microsoft.DataFactory/factories/linkedServices",
			"apiVersion": "2018-06-01",
			"properties": {
				"annotations": [],
				"type": "AzureBlobStorage",
				"typeProperties": {
					"sasUri": "[parameters('AzureBlobStorage1bysasmethod_sasUri')]"
				}
			},
			"dependsOn": []
		},
		{
			"name": "[concat(parameters('factoryName'), '/AzureBlobStorage1magedidentity')]",
			"type": "Microsoft.DataFactory/factories/linkedServices",
			"apiVersion": "2018-06-01",
			"properties": {
				"annotations": [],
				"type": "AzureBlobStorage",
				"typeProperties": {
					"serviceEndpoint": "[parameters('AzureBlobStorage1magedidentity_properties_typeProperties_serviceEndpoint')]",
					"accountKind": "StorageV2"
				}
			},
			"dependsOn": []
		},
		{
			"name": "[concat(parameters('factoryName'), '/AzureDataLakeStorage1')]",
			"type": "Microsoft.DataFactory/factories/linkedServices",
			"apiVersion": "2018-06-01",
			"properties": {
				"annotations": [],
				"type": "AzureBlobFS",
				"typeProperties": {
					"url": "[parameters('AzureDataLakeStorage1_properties_typeProperties_url')]",
					"accountKey": {
						"type": "SecureString",
						"value": "[parameters('AzureDataLakeStorage1_accountKey')]"
					}
				}
			},
			"dependsOn": []
		},
		{
			"name": "[concat(parameters('factoryName'), '/AzureKeyVault1')]",
			"type": "Microsoft.DataFactory/factories/linkedServices",
			"apiVersion": "2018-06-01",
			"properties": {
				"annotations": [],
				"type": "AzureKeyVault",
				"typeProperties": {
					"baseUrl": "[parameters('AzureKeyVault1_properties_typeProperties_baseUrl')]"
				}
			},
			"dependsOn": []
		},
		{
			"name": "[concat(parameters('factoryName'), '/AzureSqlDatabase1')]",
			"type": "Microsoft.DataFactory/factories/linkedServices",
			"apiVersion": "2018-06-01",
			"properties": {
				"annotations": [],
				"type": "AzureSqlDatabase",
				"typeProperties": {
					"server": "[parameters('AzureSqlDatabase1_properties_typeProperties_server')]",
					"database": "[parameters('AzureSqlDatabase1_properties_typeProperties_database')]",
					"encrypt": "mandatory",
					"trustServerCertificate": false,
					"authenticationType": "SystemAssignedManagedIdentity"
				}
			},
			"dependsOn": []
		},
		{
			"name": "[concat(parameters('factoryName'), '/RestService1')]",
			"type": "Microsoft.DataFactory/factories/linkedServices",
			"apiVersion": "2018-06-01",
			"properties": {
				"description": "restapilink",
				"annotations": [],
				"type": "RestService",
				"typeProperties": {
					"url": "[parameters('RestService1_properties_typeProperties_url')]",
					"enableServerCertificateValidation": false,
					"authenticationType": "Anonymous"
				}
			},
			"dependsOn": []
		},
		{
			"name": "[concat(parameters('factoryName'), '/directaccountAzureBlobStorage1')]",
			"type": "Microsoft.DataFactory/factories/linkedServices",
			"apiVersion": "2018-06-01",
			"properties": {
				"annotations": [],
				"type": "AzureBlobStorage",
				"typeProperties": {
					"connectionString": "[parameters('directaccountAzureBlobStorage1_connectionString')]"
				}
			},
			"dependsOn": []
		},
		{
			"name": "[concat(parameters('factoryName'), '/integrationRuntime1onprimesql')]",
			"type": "Microsoft.DataFactory/factories/integrationRuntimes",
			"apiVersion": "2018-06-01",
			"properties": {
				"type": "SelfHosted",
				"typeProperties": {}
			},
			"dependsOn": []
		},
		{
			"name": "[concat(parameters('factoryName'), '/tes_master_pipline')]",
			"type": "Microsoft.DataFactory/factories/pipelines",
			"apiVersion": "2018-06-01",
			"properties": {
				"activities": [
					{
						"name": "Execute Pipeline1",
						"type": "ExecutePipeline",
						"dependsOn": [],
						"policy": {
							"secureInput": false
						},
						"userProperties": [],
						"typeProperties": {
							"pipeline": {
								"referenceName": "child piepline",
								"type": "PipelineReference"
							},
							"waitOnCompletion": false,
							"parameters": {}
						}
					},
					{
						"name": "Execute Pipeline2",
						"type": "ExecutePipeline",
						"dependsOn": [
							{
								"activity": "Execute Pipeline1",
								"dependencyConditions": [
									"Succeeded"
								]
							}
						],
						"policy": {
							"secureInput": false
						},
						"userProperties": [],
						"typeProperties": {
							"pipeline": {
								"referenceName": "child2_pipeline1",
								"type": "PipelineReference"
							},
							"waitOnCompletion": false,
							"parameters": {}
						}
					}
				],
				"policy": {
					"elapsedTimeMetric": {}
				},
				"annotations": []
			},
			"dependsOn": [
				"[concat(variables('factoryId'), '/pipelines/child piepline')]",
				"[concat(variables('factoryId'), '/pipelines/child2_pipeline1')]"
			]
		},
		{
			"name": "[concat(parameters('factoryName'), '/AzureSqlTable1')]",
			"type": "Microsoft.DataFactory/factories/datasets",
			"apiVersion": "2018-06-01",
			"properties": {
				"linkedServiceName": {
					"referenceName": "AzureSqlDatabase1",
					"type": "LinkedServiceReference"
				},
				"annotations": [],
				"type": "AzureSqlTable",
				"schema": [],
				"typeProperties": {}
			},
			"dependsOn": [
				"[concat(variables('factoryId'), '/linkedServices/AzureSqlDatabase1')]"
			]
		},
		{
			"name": "[concat(parameters('factoryName'), '/AzureSqlTable2')]",
			"type": "Microsoft.DataFactory/factories/datasets",
			"apiVersion": "2018-06-01",
			"properties": {
				"linkedServiceName": {
					"referenceName": "AzureSqlDatabase1",
					"type": "LinkedServiceReference"
				},
				"annotations": [],
				"type": "AzureSqlTable",
				"schema": [],
				"typeProperties": {
					"schema": "dbo",
					"table": "emp"
				}
			},
			"dependsOn": [
				"[concat(variables('factoryId'), '/linkedServices/AzureSqlDatabase1')]"
			]
		},
		{
			"name": "[concat(parameters('factoryName'), '/DelimitedText1')]",
			"type": "Microsoft.DataFactory/factories/datasets",
			"apiVersion": "2018-06-01",
			"properties": {
				"linkedServiceName": {
					"referenceName": "directaccountAzureBlobStorage1",
					"type": "LinkedServiceReference"
				},
				"parameters": {
					"filename": {
						"type": "string"
					},
					"foldername": {
						"type": "string"
					}
				},
				"annotations": [],
				"type": "DelimitedText",
				"typeProperties": {
					"location": {
						"type": "AzureBlobStorageLocation",
						"fileName": {
							"value": "@dataset().filename",
							"type": "Expression"
						},
						"folderPath": {
							"value": "@dataset().foldername",
							"type": "Expression"
						},
						"container": "labadf"
					},
					"columnDelimiter": ",",
					"escapeChar": "\\",
					"firstRowAsHeader": true,
					"quoteChar": "\""
				},
				"schema": [
					{
						"name": "name",
						"type": "String"
					},
					{
						"name": "age ",
						"type": "String"
					},
					{
						"name": "dob",
						"type": "String"
					}
				]
			},
			"dependsOn": [
				"[concat(variables('factoryId'), '/linkedServices/directaccountAzureBlobStorage1')]"
			]
		},
		{
			"name": "[concat(parameters('factoryName'), '/DelimitedText2')]",
			"type": "Microsoft.DataFactory/factories/datasets",
			"apiVersion": "2018-06-01",
			"properties": {
				"linkedServiceName": {
					"referenceName": "AzureDataLakeStorage1",
					"type": "LinkedServiceReference"
				},
				"annotations": [],
				"type": "DelimitedText",
				"typeProperties": {
					"location": {
						"type": "AzureBlobFSLocation",
						"fileName": "emp_20241106.txt",
						"folderPath": "input/levle1",
						"fileSystem": "labadf"
					},
					"columnDelimiter": ",",
					"escapeChar": "\\",
					"firstRowAsHeader": true,
					"quoteChar": "\""
				},
				"schema": []
			},
			"dependsOn": [
				"[concat(variables('factoryId'), '/linkedServices/AzureDataLakeStorage1')]"
			]
		},
		{
			"name": "[concat(parameters('factoryName'), '/DelimitedText3')]",
			"type": "Microsoft.DataFactory/factories/datasets",
			"apiVersion": "2018-06-01",
			"properties": {
				"linkedServiceName": {
					"referenceName": "AzureDataLakeStorage1",
					"type": "LinkedServiceReference"
				},
				"annotations": [],
				"type": "DelimitedText",
				"typeProperties": {
					"location": {
						"type": "AzureBlobFSLocation",
						"fileName": "Book1.txt",
						"folderPath": "input/levle1",
						"fileSystem": "labadf"
					},
					"columnDelimiter": ",",
					"escapeChar": "\\",
					"firstRowAsHeader": true,
					"quoteChar": "\""
				},
				"schema": []
			},
			"dependsOn": [
				"[concat(variables('factoryId'), '/linkedServices/AzureDataLakeStorage1')]"
			]
		},
		{
			"name": "[concat(parameters('factoryName'), '/DelimitedText4')]",
			"type": "Microsoft.DataFactory/factories/datasets",
			"apiVersion": "2018-06-01",
			"properties": {
				"linkedServiceName": {
					"referenceName": "directaccountAzureBlobStorage1",
					"type": "LinkedServiceReference"
				},
				"annotations": [],
				"type": "DelimitedText",
				"typeProperties": {
					"location": {
						"type": "AzureBlobStorageLocation",
						"fileName": "dummy.txt",
						"folderPath": "input",
						"container": "labadf"
					},
					"columnDelimiter": ",",
					"escapeChar": "\\",
					"firstRowAsHeader": false,
					"quoteChar": "\""
				},
				"schema": [
					{
						"type": "String"
					}
				]
			},
			"dependsOn": [
				"[concat(variables('factoryId'), '/linkedServices/directaccountAzureBlobStorage1')]"
			]
		},
		{
			"name": "[concat(parameters('factoryName'), '/DelimitedText5')]",
			"type": "Microsoft.DataFactory/factories/datasets",
			"apiVersion": "2018-06-01",
			"properties": {
				"linkedServiceName": {
					"referenceName": "directaccountAzureBlobStorage1",
					"type": "LinkedServiceReference"
				},
				"annotations": [],
				"type": "DelimitedText",
				"typeProperties": {
					"location": {
						"type": "AzureBlobStorageLocation",
						"fileName": "Book1.txt",
						"folderPath": "input/levle1",
						"container": "labadf"
					},
					"columnDelimiter": ",",
					"escapeChar": "\\",
					"firstRowAsHeader": false,
					"quoteChar": "\""
				},
				"schema": []
			},
			"dependsOn": [
				"[concat(variables('factoryId'), '/linkedServices/directaccountAzureBlobStorage1')]"
			]
		},
		{
			"name": "[concat(parameters('factoryName'), '/RestResource1')]",
			"type": "Microsoft.DataFactory/factories/datasets",
			"apiVersion": "2018-06-01",
			"properties": {
				"linkedServiceName": {
					"referenceName": "RestService1",
					"type": "LinkedServiceReference"
				},
				"annotations": [],
				"type": "RestResource",
				"typeProperties": {},
				"schema": []
			},
			"dependsOn": [
				"[concat(variables('factoryId'), '/linkedServices/RestService1')]"
			]
		}
	]
}